setup.py
tinysmtp.py
tinysmtp.egg-info/PKG-INFO
tinysmtp.egg-info/SOURCES.txt
tinysmtp.egg-info/dependency_links.txt
tinysmtp.egg-info/not-zip-safe
tinysmtp.egg-info/requires.txt
tinysmtp.egg-info/top_level.txt