Metadata-Version: 1.0
Name: tinysmtp
Version: 0.1.2
Summary: Basically Flask-Mail without the Flask part
Home-page: https://github.com/rconradharris/tinysmtp
Author: Rick Harris
Author-email: rconradharris@gmail.com
License: BSD
Platform: any
Classifier: Environment :: Web Environment
Classifier: Intended Audience :: Developers
Classifier: License :: OSI Approved :: BSD License
Classifier: Operating System :: OS Independent
Classifier: Programming Language :: Python
Classifier: Topic :: Internet :: WWW/HTTP :: Dynamic Content
Classifier: Topic :: Software Development :: Libraries :: Python Modules
